{
  "train": {
    "sampled": 500,
    "total": 50000,
    "resolutions": {
      "357x500": 5,
      "500x480": 2,
      "500x361": 3,
      "500x312": 1,
      "500x333": 22,
      "500x370": 5,
      "500x379": 4,
      "500x394": 4,
      "375x500": 18,
      "344x500": 1,
      "500x486": 1,
      "500x357": 11,
      "476x500": 1,
      "500x393": 4,
      "438x500": 2,
      "500x375": 96,
      "500x359": 2,
      "500x376": 3,
      "500x354": 2,
      "500x419": 1,
      "500x363": 3,
      "500x454": 1,
      "407x500": 1,
      "500x475": 1,
      "657x599": 1,
      "388x500": 2,
      "500x416": 3,
      "500x348": 3,
      "500x374": 7,
      "500x447": 2,
      "399x500": 2,
      "382x500": 2,
      "500x397": 2,
      "428x500": 2,
      "307x299": 1,
      "500x411": 1,
      "469x500": 1,
      "499x500": 3,
      "500x387": 1,
      "500x483": 2,
      "500x431": 1,
      "500x368": 2,
      "333x500": 4,
      "381x500": 2,
      "464x500": 2,
      "500x358": 2,
      "425x500": 1,
      "500x477": 1,
      "500x474": 1,
      "500x367": 2,
      "500x334": 6,
      "500x400": 28,
      "500x500": 9,
      "500x446": 1,
      "426x500": 1,
      "500x438": 1,
      "498x500": 1,
      "500x389": 1,
      "500x386": 2,
      "378x500": 1,
      "500x390": 4,
      "500x356": 4,
      "500x437": 1,
      "500x372": 4,
      "358x500": 2,
      "600x508": 1,
      "475x500": 1,
      "500x399": 3,
      "459x500": 1,
      "500x409": 4,
      "400x500": 8,
      "460x500": 3,
      "800x533": 1,
      "424x450": 1,
      "433x500": 2,
      "500x388": 1,
      "437x437": 1,
      "479x500": 2,
      "367x500": 1,
      "439x500": 1,
      "500x434": 1,
      "640x440": 1,
      "500x402": 2,
      "447x500": 2,
      "376x500": 2,
      "768x512": 1,
      "500x435": 2,
      "500x364": 2,
      "374x500": 1,
      "480x500": 1,
      "500x452": 2,
      "500x362": 3,
      "398x500": 1,
      "500x350": 1,
      "498x444": 1,
      "400x600": 2,
      "500x373": 3,
      "500x383": 3,
      "500x380": 1,
      "483x500": 1,
      "500x384": 1,
      "500x462": 2,
      "500x470": 2,
      "600x449": 1,
      "404x500": 1,
      "505x600": 1,
      "429x500": 1,
      "500x459": 1,
      "449x500": 1,
      "500x371": 1,
      "350x500": 1,
      "897x651": 1,
      "500x471": 2,
      "396x500": 1,
      "476x434": 1,
      "500x445": 1,
      "500x432": 1,
      "500x360": 2,
      "500x381": 3,
      "354x500": 1,
      "461x500": 1,
      "500x391": 2,
      "500x467": 1,
      "412x500": 1,
      "500x366": 1,
      "500x418": 1,
      "500x349": 2,
      "605x407": 1,
      "356x500": 1,
      "335x500": 1,
      "500x444": 1,
      "325x500": 1,
      "373x500": 1,
      "500x352": 1,
      "500x369": 1,
      "500x415": 2,
      "441x500": 1,
      "491x500": 1,
      "434x500": 1,
      "463x500": 1,
      "500x456": 1,
      "500x365": 1,
      "500x332": 3,
      "900x506": 1,
      "500x323": 1,
      "500x398": 3,
      "282x500": 1,
      "500x313": 1,
      "920x671": 1,
      "500x302": 1,
      "500x417": 1,
      "500x382": 1,
      "500x351": 1,
      "355x500": 1,
      "750x656": 1,
      "700x466": 1,
      "409x500": 1,
      "430x500": 1,
      "329x500": 1,
      "458x500": 1,
      "367x334": 1,
      "448x336": 1,
      "500x337": 3,
      "500x281": 1,
      "500x443": 1,
      "395x415": 1,
      "500x378": 1,
      "444x392": 1,
      "500x465": 1,
      "500x490": 1,
      "265x280": 1,
      "500x491": 1,
      "419x500": 1,
      "390x480": 1,
      "467x500": 1,
      "433x433": 1,
      "500x428": 1,
      "500x335": 1,
      "432x628": 1,
      "500x377": 1,
      "454x500": 1,
      "500x347": 1,
      "386x500": 1,
      "446x500": 1,
      "495x500": 1,
      "500x316": 1,
      "339x500": 1,
      "397x500": 1,
      "500x396": 1,
      "500x285": 1,
      "500x255": 1,
      "738x812": 1,
      "521x620": 1,
      "369x500": 1,
      "500x353": 1,
      "1338x1536": 1,
      "681x782": 1,
      "500x355": 1,
      "451x397": 1,
      "468x500": 1,
      "800x551": 1,
      "1600x1468": 1,
      "416x500": 1,
      "480x480": 1,
      "640x635": 1,
      "650x455": 1,
      "500x495": 1,
      "500x326": 1
    },
    "formats": {
      "JPEG": 490,
      "RAW": 10
    },
    "modes": {
      "RGB": 500
    }
  },
  "validation": {
    "sampled": 500,
    "total": 10000,
    "resolutions": {
      "640x512": 1,
      "500x375": 102,
      "500x339": 3,
      "500x333": 72,
      "433x500": 1,
      "405x285": 1,
      "460x500": 1,
      "491x500": 1,
      "500x374": 4,
      "500x435": 1,
      "500x380": 3,
      "500x457": 1,
      "500x447": 2,
      "500x467": 1,
      "500x439": 2,
      "500x453": 1,
      "500x410": 1,
      "483x500": 2,
      "500x400": 11,
      "500x357": 8,
      "473x500": 2,
      "500x327": 1,
      "500x500": 6,
      "500x462": 1,
      "500x454": 1,
      "500x389": 2,
      "450x552": 1,
      "448x336": 1,
      "372x500": 2,
      "500x348": 3,
      "500x427": 1,
      "357x500": 2,
      "500x416": 1,
      "500x372": 2,
      "381x500": 1,
      "500x367": 2,
      "419x500": 1,
      "375x500": 15,
      "378x500": 1,
      "500x399": 2,
      "500x473": 1,
      "500x491": 1,
      "500x488": 1,
      "500x413": 1,
      "500x460": 1,
      "500x349": 1,
      "500x418": 3,
      "500x304": 1,
      "500x356": 3,
      "466x500": 1,
      "488x500": 1,
      "471x500": 2,
      "495x500": 1,
      "500x448": 1,
      "364x500": 1,
      "500x403": 1,
      "500x354": 1,
      "396x500": 1,
      "495x448": 1,
      "333x500": 8,
      "800x600": 3,
      "500x358": 1,
      "500x332": 9,
      "720x720": 1,
      "640x480": 3,
      "800x571": 1,
      "500x369": 3,
      "465x325": 1,
      "500x417": 1,
      "500x366": 3,
      "500x390": 2,
      "500x295": 1,
      "500x371": 1,
      "394x263": 1,
      "800x533": 2,
      "640x511": 1,
      "425x509": 1,
      "328x500": 1,
      "368x500": 1,
      "500x425": 1,
      "500x315": 1,
      "500x266": 1,
      "500x496": 1,
      "426x500": 1,
      "500x397": 1,
      "500x428": 1,
      "500x381": 1,
      "500x370": 1,
      "3600x2400": 1,
      "377x500": 1,
      "556x856": 1,
      "500x334": 14,
      "267x401": 1,
      "500x387": 1,
      "500x178": 1,
      "500x383": 2,
      "442x500": 1,
      "500x343": 1,
      "500x290": 1,
      "1200x1111": 1,
      "750x608": 1,
      "500x385": 2,
      "380x305": 1,
      "1600x1355": 1,
      "500x388": 1,
      "312x500": 1,
      "600x402": 1,
      "1280x848": 1,
      "280x218": 1,
      "500x340": 2,
      "402x402": 2,
      "138x210": 1,
      "344x283": 1,
      "500x318": 1,
      "240x180": 2,
      "365x500": 1,
      "332x500": 2,
      "500x368": 1,
      "400x300": 2,
      "500x281": 3,
      "512x344": 1,
      "600x260": 1,
      "500x426": 1,
      "650x458": 1,
      "500x489": 1,
      "1133x800": 1,
      "450x600": 1,
      "576x432": 1,
      "400x338": 1,
      "408x500": 1,
      "500x344": 1,
      "300x280": 1,
      "342x425": 1,
      "294x220": 1,
      "200x140": 1,
      "130x98": 1,
      "768x384": 1,
      "640x479": 1,
      "135x89": 1,
      "500x421": 2,
      "576x379": 1,
      "2410x3600": 1,
      "200x200": 1,
      "500x335": 1,
      "443x333": 1,
      "500x313": 1,
      "198x130": 1,
      "1024x768": 1,
      "640x361": 1,
      "472x284": 1,
      "600x400": 1,
      "500x328": 1,
      "800x608": 1,
      "210x148": 1,
      "170x146": 1,
      "316x268": 1,
      "500x338": 1,
      "480x320": 1,
      "640x458": 1,
      "766x347": 1,
      "720x540": 1,
      "224x137": 1,
      "500x326": 2,
      "289x216": 1,
      "196x169": 1,
      "800x657": 1,
      "380x254": 1,
      "276x340": 1,
      "250x180": 1,
      "205x150": 1,
      "133x100": 1,
      "378x400": 1,
      "415x283": 1,
      "180x128": 1,
      "300x200": 1,
      "320x480": 1,
      "500x284": 1,
      "470x300": 1,
      "335x500": 1,
      "460x276": 1,
      "800x603": 1,
      "1024x767": 1,
      "450x358": 1,
      "301x470": 1,
      "200x133": 1,
      "800x532": 1,
      "504x383": 1,
      "716x430": 1,
      "500x452": 1,
      "458x500": 1,
      "216x154": 1,
      "500x377": 2,
      "801x1200": 1,
      "200x160": 1,
      "500x391": 1,
      "500x423": 1,
      "500x431": 1,
      "560x442": 1,
      "331x599": 1,
      "350x500": 1,
      "1124x1487": 1,
      "500x481": 1,
      "500x248": 1,
      "500x408": 1,
      "500x331": 1,
      "500x386": 2,
      "720x480": 1,
      "540x358": 1,
      "454x500": 1,
      "374x500": 1,
      "722x471": 1,
      "800x450": 1,
      "500x337": 1,
      "358x500": 1,
      "500x429": 1,
      "500x484": 1,
      "700x525": 1
    },
    "formats": {
      "JPEG": 472,
      "RAW": 28
    },
    "modes": {
      "RGB": 499,
      "L": 1
    }
  },
  "test": {
    "sampled": 500,
    "total": 5000,
    "resolutions": {
      "500x439": 2,
      "500x456": 1,
      "500x438": 3,
      "400x500": 6,
      "492x500": 1,
      "500x464": 1,
      "479x500": 2,
      "500x500": 16,
      "500x432": 1,
      "500x493": 1,
      "403x500": 1,
      "401x500": 1,
      "452x500": 3,
      "500x435": 2,
      "423x500": 2,
      "458x500": 4,
      "426x500": 1,
      "442x500": 1,
      "469x500": 1,
      "500x422": 1,
      "500x427": 2,
      "500x400": 12,
      "500x467": 2,
      "453x500": 1,
      "500x402": 2,
      "471x500": 1,
      "472x500": 2,
      "460x500": 1,
      "414x500": 2,
      "500x403": 2,
      "435x500": 1,
      "500x446": 1,
      "500x455": 3,
      "500x418": 1,
      "477x500": 1,
      "500x431": 2,
      "500x492": 1,
      "382x500": 1,
      "500x386": 2,
      "500x393": 2,
      "500x381": 2,
      "500x428": 3,
      "500x395": 1,
      "491x500": 1,
      "500x429": 3,
      "500x470": 1,
      "500x404": 2,
      "500x375": 189,
      "500x399": 1,
      "500x401": 2,
      "391x500": 1,
      "500x458": 2,
      "375x500": 42,
      "500x460": 2,
      "500x384": 1,
      "493x500": 1,
      "377x500": 2,
      "500x425": 1,
      "500x389": 2,
      "500x382": 1,
      "500x466": 1,
      "418x500": 1,
      "428x500": 1,
      "500x380": 1,
      "500x376": 6,
      "500x498": 1,
      "500x333": 20,
      "337x500": 2,
      "500x336": 2,
      "333x500": 1,
      "500x334": 2,
      "500x335": 6,
      "500x440": 1,
      "500x379": 3,
      "500x344": 2,
      "500x357": 1,
      "500x457": 1,
      "500x371": 1,
      "500x408": 3,
      "415x500": 1,
      "476x500": 1,
      "500x484": 1,
      "381x500": 1,
      "376x500": 1,
      "500x378": 2,
      "500x385": 1,
      "473x500": 1,
      "487x500": 1,
      "482x500": 1,
      "500x387": 2,
      "387x500": 1,
      "500x453": 1,
      "500x452": 1,
      "500x475": 1,
      "500x421": 1,
      "444x500": 1,
      "395x500": 1,
      "500x499": 2,
      "454x500": 1,
      "437x500": 1,
      "500x436": 2,
      "500x450": 1,
      "500x405": 2,
      "500x430": 2,
      "449x500": 1,
      "385x500": 1,
      "464x500": 2,
      "448x500": 1,
      "500x459": 1,
      "500x396": 1,
      "500x480": 1,
      "500x454": 1,
      "500x420": 2,
      "443x500": 2,
      "445x500": 1,
      "500x377": 2,
      "398x251": 1,
      "500x229": 1,
      "500x433": 1,
      "500x261": 1,
      "500x251": 1,
      "430x304": 1,
      "411x500": 1,
      "422x500": 1,
      "478x500": 1,
      "500x188": 1,
      "500x330": 1,
      "331x500": 1,
      "500x324": 1,
      "500x274": 1,
      "400x401": 1,
      "500x253": 1,
      "500x297": 1,
      "500x374": 8,
      "500x307": 1,
      "462x500": 1,
      "316x500": 1,
      "500x394": 1,
      "379x500": 1,
      "500x264": 1,
      "314x500": 1,
      "360x270": 1,
      "225x500": 1,
      "402x248": 1,
      "335x500": 1,
      "500x362": 1,
      "480x366": 1,
      "500x383": 1,
      "500x451": 1,
      "500x365": 1,
      "500x364": 1,
      "500x352": 1,
      "399x500": 1
    },
    "formats": {
      "JPEG": 500
    },
    "modes": {
      "RGB": 483,
      "L": 17
    }
  }
}